google_ocr_mcp_server/__init__.py
google_ocr_mcp_server/__main__.py
google_ocr_mcp_server/server.py
google_ocr_mcp_server/settings.py
google_ocr_mcp_server-0.1.5.dist-info/METADATA
google_ocr_mcp_server-0.1.5.dist-info/WHEEL
google_ocr_mcp_server-0.1.5.dist-info/entry_points.txt
google_ocr_mcp_server-0.1.5.dist-info/licenses/LICENSE
google_ocr_mcp_server-0.1.5.dist-info/RECORD
