Metadata-Version: 2.4
Name: google-ocr-mcp-server
Version: 0.1.5
Summary: Google OCR MCP server
Author-email: Zerohertz <ohg3417@gmail.com>
License: MIT
License-File: LICENSE
Keywords: Agent,Artificial Intelligence,MCP,Scientific/Engineering,Software Development
Classifier: Intended Audience :: Developers
Classifier: Intended Audience :: Education
Classifier: Intended Audience :: Science/Research
Classifier: Programming Language :: Python
Classifier: Programming Language :: Python :: 3
Classifier: Topic :: Scientific/Engineering
Classifier: Topic :: Scientific/Engineering :: Artificial Intelligence
Classifier: Topic :: Scientific/Engineering :: Mathematics
Classifier: Topic :: Software Development
Requires-Python: >=3.12
Requires-Dist: google-cloud-vision>=3.10.1
Requires-Dist: loguru>=0.7.3
Requires-Dist: mcp>=1.6.0
